wrds/__init__.py
wrds/_version.py
wrds/sql.py
wrds/test.py
wrds-3.2.0.dist-info/METADATA
wrds-3.2.0.dist-info/WHEEL
wrds-3.2.0.dist-info/top_level.txt
wrds-3.2.0.dist-info/RECORD
