Metadata-Version: 2.1
Name: wrds
Version: 3.2.0
Summary: Access WRDS data through PostgreSQL in Python.
Author-email: Alex Malek <amalek@wharton.upenn.edu>, Tim Allen <tallen@wharton.upenn.edu>, Jeff VanSickle <vjef@wharton.upenn.edu>
License: BSD-3-Clause
Project-URL: Homepage, http://wrds-www.wharton.upenn.edu
Project-URL: Repository, https://github.com/wharton/wrds
Project-URL: Documentation, https://github.com/wharton/wrds/blob/master/README.md
Keywords: wrds,finance,research,crsp,compustat
Classifier: Programming Language :: Python
Classifier: Programming Language :: Python :: 3
Classifier: Programming Language :: Python :: 3.8
Classifier: Programming Language :: Python :: 3.9
Classifier: Programming Language :: Python :: 3.10
Classifier: Programming Language :: Python :: 3.11
Classifier: Programming Language :: Python :: 3.12
Classifier: Development Status :: 5 - Production/Stable
Classifier: Environment :: Console
Classifier: Intended Audience :: End Users/Desktop
Classifier: Intended Audience :: Financial and Insurance Industry
Classifier: Intended Audience :: Education
Classifier: Intended Audience :: Science/Research
Classifier: Topic :: Office/Business :: Financial
Classifier: Topic :: Scientific/Engineering :: Information Analysis
Classifier: License :: OSI Approved :: BSD License
Requires-Python: >=3.8
Requires-Dist: numpy<1.27,>=1.26
Requires-Dist: packaging<23.3
Requires-Dist: pandas<2.3,>=2.2
Requires-Dist: psycopg2-binary<2.10,>=2.9
Requires-Dist: scipy<1.13,>=1.12
Requires-Dist: sqlalchemy<2.1,>=2
